[
  {"id": "PA", "nome": "Abaetetuba"},
  {"id": "PA", "nome": "Abel Figueiredo"},
  {"id": "PA", "nome": "Acará"},
  {"id": "PA", "nome": "Afuá"},
  {"id": "PA", "nome": "Água Azul do Norte"},
  {"id": "PA", "nome": "Alenquer"},
  {"id": "PA", "nome": "Almeirim"},
  {"id": "PA", "nome": "Altamira"},
  {"id": "PA", "nome": "Anajás"},
  {"id": "PA", "nome": "Ananindeua"},
  {"id": "PA", "nome": "Anapu"},
  {"id": "PA", "nome": "Augusto Corrêa"},
  {"id": "PA", "nome": "Aurora do Pará"},
  {"id": "PA", "nome": "Aveiro"},
  {"id": "PA", "nome": "Bagre"},
  {"id": "PA", "nome": "Baião"},
  {"id": "PA", "nome": "Bannach"},
  {"id": "PA", "nome": "Barcarena"},
  {"id": "PA", "nome": "Belém", "capital": true},
  {"id": "PA", "nome": "Belterra"},
  {"id": "PA", "nome": "Benevides"},
  {"id": "PA", "nome": "Bom Jesus do Tocantins"},
  {"id": "PA", "nome": "Bonito"},
  {"id": "PA", "nome": "Bragança"},
  {"id": "PA", "nome": "Brasil Novo"},
  {"id": "PA", "nome": "Brejo Grande do Araguaia"},
  {"id": "PA", "nome": "Breu Branco"},
  {"id": "PA", "nome": "Breves"},
  {"id": "PA", "nome": "Bujaru"},
  {"id": "PA", "nome": "Cachoeira do Arari"},
  {"id": "PA", "nome": "Cachoeira do Piriá"},
  {"id": "PA", "nome": "Cametá"},
  {"id": "PA", "nome": "Canaã dos Carajás"},
  {"id": "PA", "nome": "Capanema"},
  {"id": "PA", "nome": "Capitão Poço"},
  {"id": "PA", "nome": "Castanhal"},
  {"id": "PA", "nome": "Chaves"},
  {"id": "PA", "nome": "Colares"},
  {"id": "PA", "nome": "Conceição do Araguaia"},
  {"id": "PA", "nome": "Concórdia do Pará"},
  {"id": "PA", "nome": "Cumaru do Norte"},
  {"id": "PA", "nome": "Curionópolis"},
  {"id": "PA", "nome": "Curralinho"},
  {"id": "PA", "nome": "Curuá"},
  {"id": "PA", "nome": "Curuçá"},
  {"id": "PA", "nome": "Dom Eliseu"},
  {"id": "PA", "nome": "Eldorado dos Carajás"},
  {"id": "PA", "nome": "Faro"},
  {"id": "PA", "nome": "Floresta do Araguaia"},
  {"id": "PA", "nome": "Garrafão do Norte"},
  {"id": "PA", "nome": "Goianésia do Pará"},
  {"id": "PA", "nome": "Gurupá"},
  {"id": "PA", "nome": "Igarapé-Açu"},
  {"id": "PA", "nome": "Igarapé-Miri"},
  {"id": "PA", "nome": "Inhangapi"},
  {"id": "PA", "nome": "Ipixuna do Pará"},
  {"id": "PA", "nome": "Irituia"},
  {"id": "PA", "nome": "Itaituba"},
  {"id": "PA", "nome": "Itupiranga"},
  {"id": "PA", "nome": "Jacareacanga"},
  {"id": "PA", "nome": "Jacundá"},
  {"id": "PA", "nome": "Juruti"},
  {"id": "PA", "nome": "Limoeiro do Ajuru"},
  {"id": "PA", "nome": "Mãe do Rio"},
  {"id": "PA", "nome": "Magalhães Barata"},
  {"id": "PA", "nome": "Marabá"},
  {"id": "PA", "nome": "Maracanã"},
  {"id": "PA", "nome": "Marapanim"},
  {"id": "PA", "nome": "Marituba"},
  {"id": "PA", "nome": "Medicilândia"},
  {"id": "PA", "nome": "Melgaço"},
  {"id": "PA", "nome": "Mocajuba"},
  {"id": "PA", "nome": "Moju"},
  {"id": "PA", "nome": "Monte Alegre"},
  {"id": "PA", "nome": "Muaná"},
  {"id": "PA", "nome": "Nova Esperança do Piriá"},
  {"id": "PA", "nome": "Nova Ipixuna"},
  {"id": "PA", "nome": "Nova Timboteua"},
  {"id": "PA", "nome": "Novo Progresso"},
  {"id": "PA", "nome": "Novo Repartimento"},
  {"id": "PA", "nome": "Óbidos"},
  {"id": "PA", "nome": "Oeiras do Pará"},
  {"id": "PA", "nome": "Oriximiná"},
  {"id": "PA", "nome": "Ourém"},
  {"id": "PA", "nome": "Ourilândia do Norte"},
  {"id": "PA", "nome": "Pacajá"},
  {"id": "PA", "nome": "Palestina do Pará"},
  {"id": "PA", "nome": "Paragominas"},
  {"id": "PA", "nome": "Parauapebas"},
  {"id": "PA", "nome": "Pau d'Arco"},
  {"id": "PA", "nome": "Peixe-Boi"},
  {"id": "PA", "nome": "Piçarra"},
  {"id": "PA", "nome": "Placas"},
  {"id": "PA", "nome": "Ponta de Pedras"},
  {"id": "PA", "nome": "Portel"},
  {"id": "PA", "nome": "Porto de Moz"},
  {"id": "PA", "nome": "Prainha"},
  {"id": "PA", "nome": "Primavera"},
  {"id": "PA", "nome": "Quatipuru"},
  {"id": "PA", "nome": "Redenção"},
  {"id": "PA", "nome": "Rio Maria"},
  {"id": "PA", "nome": "Rondon do Pará"},
  {"id": "PA", "nome": "Rurópolis"},
  {"id": "PA", "nome": "Salinópolis"},
  {"id": "PA", "nome": "Salvaterra"},
  {"id": "PA", "nome": "Santa Bárbara do Pará"},
  {"id": "PA", "nome": "Santa Cruz do Arari"},
  {"id": "PA", "nome": "Santa Isabel do Pará"},
  {"id": "PA", "nome": "Santa Luzia do Pará"},
  {"id": "PA", "nome": "Santa Maria das Barreiras"},
  {"id": "PA", "nome": "Santa Maria do Pará"},
  {"id": "PA", "nome": "Santana do Araguaia"},
  {"id": "PA", "nome": "Santarém"},
  {"id": "PA", "nome": "Santarém Novo"},
  {"id": "PA", "nome": "Santo Antônio do Tauá"},
  {"id": "PA", "nome": "São Caetano de Odivela"},
  {"id": "PA", "nome": "São Domingos do Araguaia"},
  {"id": "PA", "nome": "São Domingos do Capim"},
  {"id": "PA", "nome": "São Félix do Xingu"},
  {"id": "PA", "nome": "São Francisco do Pará"},
  {"id": "PA", "nome": "São Geraldo do Araguaia"},
  {"id": "PA", "nome": "São João da Ponta"},
  {"id": "PA", "nome": "São João de Pirabas"},
  {"id": "PA", "nome": "São João do Araguaia"},
  {"id": "PA", "nome": "São Miguel do Guamá"},
  {"id": "PA", "nome": "São Sebastião da Boa Vista"},
  {"id": "PA", "nome": "Sapucaia"},
  {"id": "PA", "nome": "Senador José Porfírio"},
  {"id": "PA", "nome": "Soure"},
  {"id": "PA", "nome": "Tailândia"},
  {"id": "PA", "nome": "Terra Alta"},
  {"id": "PA", "nome": "Terra Santa"},
  {"id": "PA", "nome": "Tomé-Açu"},
  {"id": "PA", "nome": "Tracuateua"},
  {"id": "PA", "nome": "Trairão"},
  {"id": "PA", "nome": "Tucumã"},
  {"id": "PA", "nome": "Tucuruí"},
  {"id": "PA", "nome": "Ulianópolis"},
  {"id": "PA", "nome": "Uruará"},
  {"id": "PA", "nome": "Vigia"},
  {"id": "PA", "nome": "Viseu"},
  {"id": "PA", "nome": "Vitória do Xingu"},
  {"id": "PA", "nome": "Xinguara"}
]
