[
  {"id": "PI", "nome": "Acauã"},
  {"id": "PI", "nome": "Agricolândia"},
  {"id": "PI", "nome": "Água Branca"},
  {"id": "PI", "nome": "Alagoinha do Piauí"},
  {"id": "PI", "nome": "Alegrete do Piauí"},
  {"id": "PI", "nome": "Alto Longá"},
  {"id": "PI", "nome": "Altos"},
  {"id": "PI", "nome": "Alvorada do Gurguéia"},
  {"id": "PI", "nome": "Amarante"},
  {"id": "PI", "nome": "Angical do Piauí"},
  {"id": "PI", "nome": "Anísio de Abreu"},
  {"id": "PI", "nome": "Antônio Almeida"},
  {"id": "PI", "nome": "Aroazes"},
  {"id": "PI", "nome": "Arraial"},
  {"id": "PI", "nome": "Assunção do Piauí"},
  {"id": "PI", "nome": "Avelino Lopes"},
  {"id": "PI", "nome": "Baixa Grande do Ribeiro"},
  {"id": "PI", "nome": "Barra d'Alcântara"},
  {"id": "PI", "nome": "Barras"},
  {"id": "PI", "nome": "Barreiras do Piauí"},
  {"id": "PI", "nome": "Barro Duro"},
  {"id": "PI", "nome": "Batalha"},
  {"id": "PI", "nome": "Bela Vista do Piauí"},
  {"id": "PI", "nome": "Belém do Piauí"},
  {"id": "PI", "nome": "Beneditinos"},
  {"id": "PI", "nome": "Bertolínia"},
  {"id": "PI", "nome": "Betânia do Piauí"},
  {"id": "PI", "nome": "Boa Hora"},
  {"id": "PI", "nome": "Bocaina"},
  {"id": "PI", "nome": "Bom Jesus"},
  {"id": "PI", "nome": "Bom Princípio do Piauí"},
  {"id": "PI", "nome": "Bonfim do Piauí"},
  {"id": "PI", "nome": "Boqueirão do Piauí"},
  {"id": "PI", "nome": "Brasileira"},
  {"id": "PI", "nome": "Brejo do Piauí"},
  {"id": "PI", "nome": "Buriti dos Lopes"},
  {"id": "PI", "nome": "Buriti dos Montes"},
  {"id": "PI", "nome": "Cabeceiras do Piauí"},
  {"id": "PI", "nome": "Cajazeiras do Piauí"},
  {"id": "PI", "nome": "Cajueiro da Praia"},
  {"id": "PI", "nome": "Caldeirão Grande do Piauí"},
  {"id": "PI", "nome": "Campinas do Piauí"},
  {"id": "PI", "nome": "Campo Alegre do Fidalgo"},
  {"id": "PI", "nome": "Campo Grande do Piauí"},
  {"id": "PI", "nome": "Campo Largo do Piauí"},
  {"id": "PI", "nome": "Campo Maior"},
  {"id": "PI", "nome": "Canavieira"},
  {"id": "PI", "nome": "Canto do Buriti"},
  {"id": "PI", "nome": "Capitão de Campos"},
  {"id": "PI", "nome": "Capitão Gervásio Oliveira"},
  {"id": "PI", "nome": "Caracol"},
  {"id": "PI", "nome": "Caraúbas do Piauí"},
  {"id": "PI", "nome": "Caridade do Piauí"},
  {"id": "PI", "nome": "Castelo do Piauí"},
  {"id": "PI", "nome": "Caxingó"},
  {"id": "PI", "nome": "Cocal"},
  {"id": "PI", "nome": "Cocal de Telha"},
  {"id": "PI", "nome": "Cocal dos Alves"},
  {"id": "PI", "nome": "Coivaras"},
  {"id": "PI", "nome": "Colônia do Gurguéia"},
  {"id": "PI", "nome": "Colônia do Piauí"},
  {"id": "PI", "nome": "Conceição do Canindé"},
  {"id": "PI", "nome": "Coronel José Dias"},
  {"id": "PI", "nome": "Corrente"},
  {"id": "PI", "nome": "Cristalândia do Piauí"},
  {"id": "PI", "nome": "Cristino Castro"},
  {"id": "PI", "nome": "Curimatá"},
  {"id": "PI", "nome": "Currais"},
  {"id": "PI", "nome": "Curral Novo do Piauí"},
  {"id": "PI", "nome": "Curralinhos"},
  {"id": "PI", "nome": "Demerval Lobão"},
  {"id": "PI", "nome": "Dirceu Arcoverde"},
  {"id": "PI", "nome": "Dom Expedito Lopes"},
  {"id": "PI", "nome": "Dom Inocêncio"},
  {"id": "PI", "nome": "Domingos Mourão"},
  {"id": "PI", "nome": "Elesbão Veloso"},
  {"id": "PI", "nome": "Eliseu Martins"},
  {"id": "PI", "nome": "Esperantina"},
  {"id": "PI", "nome": "Fartura do Piauí"},
  {"id": "PI", "nome": "Flores do Piauí"},
  {"id": "PI", "nome": "Floresta do Piauí"},
  {"id": "PI", "nome": "Floriano"},
  {"id": "PI", "nome": "Francinópolis"},
  {"id": "PI", "nome": "Francisco Ayres"},
  {"id": "PI", "nome": "Francisco Macedo"},
  {"id": "PI", "nome": "Francisco Santos"},
  {"id": "PI", "nome": "Fronteiras"},
  {"id": "PI", "nome": "Geminiano"},
  {"id": "PI", "nome": "Gilbués"},
  {"id": "PI", "nome": "Guadalupe"},
  {"id": "PI", "nome": "Guaribas"},
  {"id": "PI", "nome": "Hugo Napoleão"},
  {"id": "PI", "nome": "Ilha Grande"},
  {"id": "PI", "nome": "Inhuma"},
  {"id": "PI", "nome": "Ipiranga do Piauí"},
  {"id": "PI", "nome": "Isaías Coelho"},
  {"id": "PI", "nome": "Itainópolis"},
  {"id": "PI", "nome": "Itaueira"},
  {"id": "PI", "nome": "Jacobina do Piauí"},
  {"id": "PI", "nome": "Jaicós"},
  {"id": "PI", "nome": "Jardim do Mulato"},
  {"id": "PI", "nome": "Jatobá do Piauí"},
  {"id": "PI", "nome": "Jerumenha"},
  {"id": "PI", "nome": "João Costa"},
  {"id": "PI", "nome": "Joaquim Pires"},
  {"id": "PI", "nome": "Joca Marques"},
  {"id": "PI", "nome": "José de Freitas"},
  {"id": "PI", "nome": "Juazeiro do Piauí"},
  {"id": "PI", "nome": "Júlio Borges"},
  {"id": "PI", "nome": "Jurema"},
  {"id": "PI", "nome": "Lagoa Alegre"},
  {"id": "PI", "nome": "Lagoa de São Francisco"},
  {"id": "PI", "nome": "Lagoa do Barro do Piauí"},
  {"id": "PI", "nome": "Lagoa do Piauí"},
  {"id": "PI", "nome": "Lagoa do Sítio"},
  {"id": "PI", "nome": "Lagoinha do Piauí"},
  {"id": "PI", "nome": "Landri Sales"},
  {"id": "PI", "nome": "Luís Correia"},
  {"id": "PI", "nome": "Luzilândia"},
  {"id": "PI", "nome": "Madeiro"},
  {"id": "PI", "nome": "Manoel Emídio"},
  {"id": "PI", "nome": "Marcolândia"},
  {"id": "PI", "nome": "Marcos Parente"},
  {"id": "PI", "nome": "Massapê do Piauí"},
  {"id": "PI", "nome": "Matias Olímpio"},
  {"id": "PI", "nome": "Miguel Alves"},
  {"id": "PI", "nome": "Miguel Leão"},
  {"id": "PI", "nome": "Milton Brandão"},
  {"id": "PI", "nome": "Monsenhor Gil"},
  {"id": "PI", "nome": "Monsenhor Hipólito"},
  {"id": "PI", "nome": "Monte Alegre do Piauí"},
  {"id": "PI", "nome": "Morro Cabeça no Tempo"},
  {"id": "PI", "nome": "Morro do Chapéu do Piauí"},
  {"id": "PI", "nome": "Murici dos Portelas"},
  {"id": "PI", "nome": "Nazaré do Piauí"},
  {"id": "PI", "nome": "Nossa Senhora de Nazaré"},
  {"id": "PI", "nome": "Nossa Senhora dos Remédios"},
  {"id": "PI", "nome": "Nova Santa Rita"},
  {"id": "PI", "nome": "Novo Oriente do Piauí"},
  {"id": "PI", "nome": "Novo Santo Antônio"},
  {"id": "PI", "nome": "Oeiras"},
  {"id": "PI", "nome": "Olho d'Água do Piauí"},
  {"id": "PI", "nome": "Padre Marcos"},
  {"id": "PI", "nome": "Paes Landim"},
  {"id": "PI", "nome": "Pajeú do Piauí"},
  {"id": "PI", "nome": "Palmeira do Piauí"},
  {"id": "PI", "nome": "Palmeirais"},
  {"id": "PI", "nome": "Paquetá"},
  {"id": "PI", "nome": "Parnaguá"},
  {"id": "PI", "nome": "Parnaíba"},
  {"id": "PI", "nome": "Passagem Franca do Piauí"},
  {"id": "PI", "nome": "Patos do Piauí"},
  {"id": "PI", "nome": "Pau d'Arco do Piauí"},
  {"id": "PI", "nome": "Paulistana"},
  {"id": "PI", "nome": "Pavussu"},
  {"id": "PI", "nome": "Pedro II"},
  {"id": "PI", "nome": "Pedro Laurentino"},
  {"id": "PI", "nome": "Picos"},
  {"id": "PI", "nome": "Pimenteiras"},
  {"id": "PI", "nome": "Pio IX"},
  {"id": "PI", "nome": "Piracuruca"},
  {"id": "PI", "nome": "Piripiri"},
  {"id": "PI", "nome": "Porto"},
  {"id": "PI", "nome": "Porto Alegre do Piauí"},
  {"id": "PI", "nome": "Prata do Piauí"},
  {"id": "PI", "nome": "Queimada Nova"},
  {"id": "PI", "nome": "Redenção do Gurguéia"},
  {"id": "PI", "nome": "Regeneração"},
  {"id": "PI", "nome": "Riacho Frio"},
  {"id": "PI", "nome": "Ribeira do Piauí"},
  {"id": "PI", "nome": "Ribeiro Gonçalves"},
  {"id": "PI", "nome": "Rio Grande do Piauí"},
  {"id": "PI", "nome": "Santa Cruz do Piauí"},
  {"id": "PI", "nome": "Santa Cruz dos Milagres"},
  {"id": "PI", "nome": "Santa Filomena"},
  {"id": "PI", "nome": "Santa Luz"},
  {"id": "PI", "nome": "Santa Rosa do Piauí"},
  {"id": "PI", "nome": "Santana do Piauí"},
  {"id": "PI", "nome": "Santo Antônio de Lisboa"},
  {"id": "PI", "nome": "Santo Antônio dos Milagres"},
  {"id": "PI", "nome": "Santo Inácio do Piauí"},
  {"id": "PI", "nome": "São Braz do Piauí"},
  {"id": "PI", "nome": "São Félix do Piauí"},
  {"id": "PI", "nome": "São Francisco de Assis do Piauí"},
  {"id": "PI", "nome": "São Francisco do Piauí"},
  {"id": "PI", "nome": "São Gonçalo do Gurguéia"},
  {"id": "PI", "nome": "São Gonçalo do Piauí"},
  {"id": "PI", "nome": "São João da Canabrava"},
  {"id": "PI", "nome": "São João da Fronteira"},
  {"id": "PI", "nome": "São João da Serra"},
  {"id": "PI", "nome": "São João da Varjota"},
  {"id": "PI", "nome": "São João do Arraial"},
  {"id": "PI", "nome": "São João do Piauí"},
  {"id": "PI", "nome": "São José do Divino"},
  {"id": "PI", "nome": "São José do Peixe"},
  {"id": "PI", "nome": "São José do Piauí"},
  {"id": "PI", "nome": "São Julião"},
  {"id": "PI", "nome": "São Lourenço do Piauí"},
  {"id": "PI", "nome": "São Luis do Piauí"},
  {"id": "PI", "nome": "São Miguel da Baixa Grande"},
  {"id": "PI", "nome": "São Miguel do Fidalgo"},
  {"id": "PI", "nome": "São Miguel do Tapuio"},
  {"id": "PI", "nome": "São Pedro do Piauí"},
  {"id": "PI", "nome": "São Raimundo Nonato"},
  {"id": "PI", "nome": "Sebastião Barros"},
  {"id": "PI", "nome": "Sebastião Leal"},
  {"id": "PI", "nome": "Sigefredo Pacheco"},
  {"id": "PI", "nome": "Simões"},
  {"id": "PI", "nome": "Simplício Mendes"},
  {"id": "PI", "nome": "Socorro do Piauí"},
  {"id": "PI", "nome": "Sussuapara"},
  {"id": "PI", "nome": "Tamboril do Piauí"},
  {"id": "PI", "nome": "Tanque do Piauí"},
  {"id": "PI", "nome": "Teresina", "capital": true},
  {"id": "PI", "nome": "União"},
  {"id": "PI", "nome": "Uruçuí"},
  {"id": "PI", "nome": "Valença do Piauí"},
  {"id": "PI", "nome": "Várzea Branca"},
  {"id": "PI", "nome": "Várzea Grande"},
  {"id": "PI", "nome": "Vera Mendes"},
  {"id": "PI", "nome": "Vila Nova do Piauí"},
  {"id": "PI", "nome": "Wall Ferraz"}
]
